<annotation>
	<folder></folder>
	<filename>liontari_liontari_images-8-_jpg.rf.7378976530d007cf12efbd4cd5958d4d.jpg</filename>
	<path>liontari_liontari_images-8-_jpg.rf.7378976530d007cf12efbd4cd5958d4d.jpg</path>
	<source>
		<database>roboflow.com</database>
	</source>
	<size>
		<width>1280</width>
		<height>640</height>
		<depth>3</depth>
	</size>
	<segmented>0</segmented>
	<object>
		<name>Liontaria</name>
		<pose>Unspecified</pose>
		<truncated>0</truncated>
		<difficult>0</difficult>
		<occluded>0</occluded>
		<bndbox>
			<xmin>125</xmin>
			<xmax>1220</xmax>
			<ymin>203</ymin>
			<ymax>500</ymax>
		</bndbox>
	</object>
</annotation>
